{
  "valid": true,
  "file_path": "src/consciousness-knowledge/evolution_state.py",
  "timestamp": 1761383597.8139818,
  "checks": {
    "syntax": {
      "valid": true,
      "score": 1.0,
      "message": "Syntax valid"
    },
    "imports": {
      "valid": true,
      "score": 1.0,
      "message": "Import syntax clean"
    },
    "complexity": {
      "valid": true,
      "score": 1.0,
      "message": "Complexity acceptable (1.3)"
    },
    "size": {
      "valid": true,
      "score": 1.0,
      "message": "Size acceptable: 68/68 lines"
    }
  },
  "quality_score": 1.0
}